{
    "ultima_atualizacao": "2026-06-23 17:33:10",
    "total_jogos_finalizados": 45,
    "resultados": [
        {
            "sigla_mandante": "MEX",
            "mandante": "México",
            "gols_mandante": 2,
            "gols_visitante": 0,
            "sigla_visitante": "RSA",
            "visitante": "África do Sul",
            "status": "Finalizado",
            "atualizado_em": "2026-06-23 17:33:10"
        },
        {
            "sigla_mandante": "KOR",
            "mandante": "Coreia do Sul",
            "gols_mandante": 2,
            "gols_visitante": 1,
            "sigla_visitante": "CZE",
            "visitante": "República Tcheca",
            "status": "Finalizado",
            "atualizado_em": "2026-06-23 17:33:10"
        },
        {
            "sigla_mandante": "CAN",
            "mandante": "Canadá",
            "gols_mandante": 1,
            "gols_visitante": 1,
            "sigla_visitante": "BIH",
            "visitante": "Bósnia",
            "status": "Finalizado",
            "atualizado_em": "2026-06-23 17:33:10"
        },
        {
            "sigla_mandante": "USA",
            "mandante": "EUA",
            "gols_mandante": 4,
            "gols_visitante": 1,
            "sigla_visitante": "PAR",
            "visitante": "Paraguai",
            "status": "Finalizado",
            "atualizado_em": "2026-06-23 17:33:10"
        },
        {
            "sigla_mandante": "QAT",
            "mandante": "Catar",
            "gols_mandante": 1,
            "gols_visitante": 1,
            "sigla_visitante": "SUI",
            "visitante": "Suíça",
            "status": "Finalizado",
            "atualizado_em": "2026-06-23 17:33:10"
        },
        {
            "sigla_mandante": "BRA",
            "mandante": "Brasil",
            "gols_mandante": 1,
            "gols_visitante": 1,
            "sigla_visitante": "MAR",
            "visitante": "Marrocos",
            "status": "Finalizado",
            "atualizado_em": "2026-06-23 17:33:10"
        },
        {
            "sigla_mandante": "HAI",
            "mandante": "Haiti",
            "gols_mandante": 0,
            "gols_visitante": 1,
            "sigla_visitante": "SCO",
            "visitante": "Escócia",
            "status": "Finalizado",
            "atualizado_em": "2026-06-23 17:33:10"
        },
        {
            "sigla_mandante": "AUS",
            "mandante": "Austrália",
            "gols_mandante": 2,
            "gols_visitante": 0,
            "sigla_visitante": "TUR",
            "visitante": "Turquia",
            "status": "Finalizado",
            "atualizado_em": "2026-06-23 17:33:10"
        },
        {
            "sigla_mandante": "GER",
            "mandante": "Alemanha",
            "gols_mandante": 7,
            "gols_visitante": 1,
            "sigla_visitante": "CUW",
            "visitante": "Curaçao",
            "status": "Finalizado",
            "atualizado_em": "2026-06-23 17:33:10"
        },
        {
            "sigla_mandante": "NED",
            "mandante": "Holanda",
            "gols_mandante": 2,
            "gols_visitante": 2,
            "sigla_visitante": "JPN",
            "visitante": "Japão",
            "status": "Finalizado",
            "atualizado_em": "2026-06-23 17:33:10"
        },
        {
            "sigla_mandante": "CIV",
            "mandante": "Costa do Marfim",
            "gols_mandante": 1,
            "gols_visitante": 0,
            "sigla_visitante": "ECU",
            "visitante": "Equador",
            "status": "Finalizado",
            "atualizado_em": "2026-06-23 17:33:10"
        },
        {
            "sigla_mandante": "SWE",
            "mandante": "Suécia",
            "gols_mandante": 5,
            "gols_visitante": 1,
            "sigla_visitante": "TUN",
            "visitante": "Tunísia",
            "status": "Finalizado",
            "atualizado_em": "2026-06-23 17:33:10"
        },
        {
            "sigla_mandante": "ESP",
            "mandante": "Espanha",
            "gols_mandante": 0,
            "gols_visitante": 0,
            "sigla_visitante": "CPV",
            "visitante": "Cabo Verde",
            "status": "Finalizado",
            "atualizado_em": "2026-06-23 17:33:10"
        },
        {
            "sigla_mandante": "BEL",
            "mandante": "Bélgica",
            "gols_mandante": 1,
            "gols_visitante": 1,
            "sigla_visitante": "EGY",
            "visitante": "Egito",
            "status": "Finalizado",
            "atualizado_em": "2026-06-23 17:33:10"
        },
        {
            "sigla_mandante": "KSA",
            "mandante": "Arábia Saudita",
            "gols_mandante": 1,
            "gols_visitante": 1,
            "sigla_visitante": "URU",
            "visitante": "Uruguai",
            "status": "Finalizado",
            "atualizado_em": "2026-06-23 17:33:10"
        },
        {
            "sigla_mandante": "IRN",
            "mandante": "Irã",
            "gols_mandante": 2,
            "gols_visitante": 2,
            "sigla_visitante": "NZL",
            "visitante": "Nova Zelândia",
            "status": "Finalizado",
            "atualizado_em": "2026-06-23 17:33:10"
        },
        {
            "sigla_mandante": "FRA",
            "mandante": "França",
            "gols_mandante": 3,
            "gols_visitante": 1,
            "sigla_visitante": "SEN",
            "visitante": "Senegal",
            "status": "Finalizado",
            "atualizado_em": "2026-06-23 17:33:10"
        },
        {
            "sigla_mandante": "IRQ",
            "mandante": "Iraque",
            "gols_mandante": 1,
            "gols_visitante": 4,
            "sigla_visitante": "NOR",
            "visitante": "Noruega",
            "status": "Finalizado",
            "atualizado_em": "2026-06-23 17:33:10"
        },
        {
            "sigla_mandante": "ARG",
            "mandante": "Argentina",
            "gols_mandante": 3,
            "gols_visitante": 0,
            "sigla_visitante": "ALG",
            "visitante": "Argélia",
            "status": "Finalizado",
            "atualizado_em": "2026-06-23 17:33:10"
        },
        {
            "sigla_mandante": "AUT",
            "mandante": "Áustria",
            "gols_mandante": 3,
            "gols_visitante": 1,
            "sigla_visitante": "JOR",
            "visitante": "Jordânia",
            "status": "Finalizado",
            "atualizado_em": "2026-06-23 17:33:10"
        },
        {
            "sigla_mandante": "POR",
            "mandante": "Portugal",
            "gols_mandante": 1,
            "gols_visitante": 1,
            "sigla_visitante": "COD",
            "visitante": "RD Congo",
            "status": "Finalizado",
            "atualizado_em": "2026-06-23 17:33:10"
        },
        {
            "sigla_mandante": "ENG",
            "mandante": "Inglaterra",
            "gols_mandante": 4,
            "gols_visitante": 2,
            "sigla_visitante": "CRO",
            "visitante": "Croácia",
            "status": "Finalizado",
            "atualizado_em": "2026-06-23 17:33:10"
        },
        {
            "sigla_mandante": "GHA",
            "mandante": "Gana",
            "gols_mandante": 1,
            "gols_visitante": 0,
            "sigla_visitante": "PAN",
            "visitante": "Panamá",
            "status": "Finalizado",
            "atualizado_em": "2026-06-23 17:33:10"
        },
        {
            "sigla_mandante": "UZB",
            "mandante": "Uzbequistão",
            "gols_mandante": 1,
            "gols_visitante": 3,
            "sigla_visitante": "COL",
            "visitante": "Colômbia",
            "status": "Finalizado",
            "atualizado_em": "2026-06-23 17:33:10"
        },
        {
            "sigla_mandante": "CZE",
            "mandante": "República Tcheca",
            "gols_mandante": 1,
            "gols_visitante": 1,
            "sigla_visitante": "RSA",
            "visitante": "África do Sul",
            "status": "Finalizado",
            "atualizado_em": "2026-06-23 17:33:10"
        },
        {
            "sigla_mandante": "SUI",
            "mandante": "Suíça",
            "gols_mandante": 4,
            "gols_visitante": 1,
            "sigla_visitante": "BIH",
            "visitante": "Bósnia",
            "status": "Finalizado",
            "atualizado_em": "2026-06-23 17:33:10"
        },
        {
            "sigla_mandante": "CAN",
            "mandante": "Canadá",
            "gols_mandante": 6,
            "gols_visitante": 0,
            "sigla_visitante": "QAT",
            "visitante": "Catar",
            "status": "Finalizado",
            "atualizado_em": "2026-06-23 17:33:10"
        },
        {
            "sigla_mandante": "MEX",
            "mandante": "México",
            "gols_mandante": 1,
            "gols_visitante": 0,
            "sigla_visitante": "KOR",
            "visitante": "Coreia do Sul",
            "status": "Finalizado",
            "atualizado_em": "2026-06-23 17:33:10"
        },
        {
            "sigla_mandante": "USA",
            "mandante": "EUA",
            "gols_mandante": 2,
            "gols_visitante": 0,
            "sigla_visitante": "AUS",
            "visitante": "Austrália",
            "status": "Finalizado",
            "atualizado_em": "2026-06-23 17:33:10"
        },
        {
            "sigla_mandante": "SCO",
            "mandante": "Escócia",
            "gols_mandante": 0,
            "gols_visitante": 1,
            "sigla_visitante": "MAR",
            "visitante": "Marrocos",
            "status": "Finalizado",
            "atualizado_em": "2026-06-23 17:33:10"
        },
        {
            "sigla_mandante": "BRA",
            "mandante": "Brasil",
            "gols_mandante": 3,
            "gols_visitante": 0,
            "sigla_visitante": "HAI",
            "visitante": "Haiti",
            "status": "Finalizado",
            "atualizado_em": "2026-06-23 17:33:10"
        },
        {
            "sigla_mandante": "TUR",
            "mandante": "Turquia",
            "gols_mandante": 0,
            "gols_visitante": 1,
            "sigla_visitante": "PAR",
            "visitante": "Paraguai",
            "status": "Finalizado",
            "atualizado_em": "2026-06-23 17:33:10"
        },
        {
            "sigla_mandante": "NED",
            "mandante": "Holanda",
            "gols_mandante": 5,
            "gols_visitante": 1,
            "sigla_visitante": "SWE",
            "visitante": "Suécia",
            "status": "Finalizado",
            "atualizado_em": "2026-06-23 17:33:10"
        },
        {
            "sigla_mandante": "GER",
            "mandante": "Alemanha",
            "gols_mandante": 2,
            "gols_visitante": 1,
            "sigla_visitante": "CIV",
            "visitante": "Costa do Marfim",
            "status": "Finalizado",
            "atualizado_em": "2026-06-23 17:33:10"
        },
        {
            "sigla_mandante": "ECU",
            "mandante": "Equador",
            "gols_mandante": 0,
            "gols_visitante": 0,
            "sigla_visitante": "CUW",
            "visitante": "Curaçao",
            "status": "Finalizado",
            "atualizado_em": "2026-06-23 17:33:10"
        },
        {
            "sigla_mandante": "TUN",
            "mandante": "Tunísia",
            "gols_mandante": 0,
            "gols_visitante": 4,
            "sigla_visitante": "JPN",
            "visitante": "Japão",
            "status": "Finalizado",
            "atualizado_em": "2026-06-23 17:33:10"
        },
        {
            "sigla_mandante": "ESP",
            "mandante": "Espanha",
            "gols_mandante": 4,
            "gols_visitante": 0,
            "sigla_visitante": "KSA",
            "visitante": "Arábia Saudita",
            "status": "Finalizado",
            "atualizado_em": "2026-06-23 17:33:10"
        },
        {
            "sigla_mandante": "BEL",
            "mandante": "Bélgica",
            "gols_mandante": 0,
            "gols_visitante": 0,
            "sigla_visitante": "IRN",
            "visitante": "Irã",
            "status": "Finalizado",
            "atualizado_em": "2026-06-23 17:33:10"
        },
        {
            "sigla_mandante": "URU",
            "mandante": "Uruguai",
            "gols_mandante": 2,
            "gols_visitante": 2,
            "sigla_visitante": "CPV",
            "visitante": "Cabo Verde",
            "status": "Finalizado",
            "atualizado_em": "2026-06-23 17:33:10"
        },
        {
            "sigla_mandante": "NZL",
            "mandante": "Nova Zelândia",
            "gols_mandante": 1,
            "gols_visitante": 3,
            "sigla_visitante": "EGY",
            "visitante": "Egito",
            "status": "Finalizado",
            "atualizado_em": "2026-06-23 17:33:10"
        },
        {
            "sigla_mandante": "ARG",
            "mandante": "Argentina",
            "gols_mandante": 2,
            "gols_visitante": 0,
            "sigla_visitante": "AUT",
            "visitante": "Áustria",
            "status": "Finalizado",
            "atualizado_em": "2026-06-23 17:33:10"
        },
        {
            "sigla_mandante": "FRA",
            "mandante": "França",
            "gols_mandante": 3,
            "gols_visitante": 0,
            "sigla_visitante": "IRQ",
            "visitante": "Iraque",
            "status": "Finalizado",
            "atualizado_em": "2026-06-23 17:33:10"
        },
        {
            "sigla_mandante": "NOR",
            "mandante": "Noruega",
            "gols_mandante": 3,
            "gols_visitante": 2,
            "sigla_visitante": "SEN",
            "visitante": "Senegal",
            "status": "Finalizado",
            "atualizado_em": "2026-06-23 17:33:10"
        },
        {
            "sigla_mandante": "JOR",
            "mandante": "Jordânia",
            "gols_mandante": 1,
            "gols_visitante": 2,
            "sigla_visitante": "ALG",
            "visitante": "Argélia",
            "status": "Finalizado",
            "atualizado_em": "2026-06-23 17:33:10"
        },
        {
            "sigla_mandante": "POR",
            "mandante": "Portugal",
            "gols_mandante": 5,
            "gols_visitante": 0,
            "sigla_visitante": "UZB",
            "visitante": "Uzbequistão",
            "status": "Finalizado",
            "atualizado_em": "2026-06-23 17:33:10"
        }
    ]
}